PasswordLockFSM.v
`timescale 1ns / 1ps

module PasswordLockFSM (
    input clk,
    input reset,
    input admin_mode,
    input [3:0] key_in,
    input key_valid,
    output reg unlock,
    output reg locked_out,
    output reg error_led,
    output reg [2:0] state  // For debug
);

// FSM States
localparam IDLE         = 3'd0,
           INPUT_1      = 3'd1,
           INPUT_2      = 3'd2,
           INPUT_3      = 3'd3,
           INPUT_4      = 3'd4,
           UNLOCKED     = 3'd5,
           LOCKED       = 3'd6;

reg [3:0] stored_password[3:0]; // 4-digit password
reg [3:0] user_input[3:0];
reg [1:0] input_index;
reg [1:0] attempt_count;
reg [3:0] lockout_timer;
reg [3:0] timeout_counter;

wire input_timeout = (timeout_counter >= 4'd10);

integer i;

always @(posedge clk or posedge reset) begin
    if (reset) begin
        state <= IDLE;
        unlock <= 0;
        locked_out <= 0;
        error_led <= 0;
        attempt_count <= 0;
        lockout_timer <= 0;
        timeout_counter <= 0;

        // Default password: 4'b1010_0101_0011_1100
        stored_password[0] <= 4'b1010;
        stored_password[1] <= 4'b0101;
        stored_password[2] <= 4'b0011;
        stored_password[3] <= 4'b1100;

    end else begin
        timeout_counter <= timeout_counter + 1;

        // Lockout mode
        if (locked_out) begin
            lockout_timer <= lockout_timer - 1;
            if (lockout_timer == 0) begin
                locked_out <= 0;
                attempt_count <= 0;
                state <= IDLE;
            end
        end

        if (!locked_out) begin
            case (state)
                IDLE: begin
                    unlock <= 0;
                    error_led <= 0;
                    input_index <= 0;
                    if (key_valid) begin
                        user_input[0] <= key_in;
                        input_index <= 1;
                        state <= INPUT_1;
                        timeout_counter <= 0;
                    end
                end

                INPUT_1, INPUT_2, INPUT_3: begin
                    if (key_valid) begin
                        user_input[input_index] <= key_in;
                        input_index <= input_index + 1;
                        state <= state + 1;
                        timeout_counter <= 0;
                    end else if (input_timeout) begin
                        state <= IDLE;
                    end
                end

                INPUT_4: begin
                    if (key_valid) begin
                        user_input[3] <= key_in;
                        timeout_counter <= 0;

                        if (admin_mode) begin
                            // Change password
                            for (i = 0; i < 4; i = i + 1)
                                stored_password[i] <= user_input[i];
                            state <= IDLE;
                        end else begin
                            // Check password
                            if ((user_input[0] == stored_password[0]) &&
                                (user_input[1] == stored_password[1]) &&
                                (user_input[2] == stored_password[2]) &&
                                (user_input[3] == stored_password[3])) begin
                                unlock <= 1;
                                error_led <= 0;
                                state <= UNLOCKED;
                            end else begin
                                attempt_count <= attempt_count + 1;
                                error_led <= 1;
                                unlock <= 0;

                                if (attempt_count == 2) begin
                                    locked_out <= 1;
                                    lockout_timer <= 4'd10;
                                    state <= LOCKED;
                                end else begin
                                    state <= IDLE;
                                end
                            end
                        end
                    end else if (input_timeout) begin
                        state <= IDLE;
                    end
                end

                UNLOCKED: begin
                    // Unlock will stay for a short period
                    unlock <= 0;
                    state <= IDLE;
                end

                LOCKED: begin
                    // Wait handled above
                    error_led <= 0;
                    unlock <= 0;
                end

            endcase
        end
    end
end

endmodule

PasswordLockFSM_tb.v
`timescale 1ns / 1ps

module PasswordLockFSM_tb;

reg clk, reset, admin_mode, key_valid;
reg [3:0] key_in;
wire unlock, locked_out, error_led;
wire [2:0] state;

PasswordLockFSM dut (
    .clk(clk),
    .reset(reset),
    .admin_mode(admin_mode),
    .key_in(key_in),
    .key_valid(key_valid),
    .unlock(unlock),
    .locked_out(locked_out),
    .error_led(error_led),
    .state(state)
);

// Clock generation
initial clk = 0;
always #5 clk = ~clk;

task enter_password;
    input [15:0] password;
    integer i;
    begin
        for (i = 12; i >= 0; i = i - 4) begin
            key_in = password[i +: 4];
            key_valid = 1;
            #10;
            key_valid = 0;
            #10;
        end
    end
endtask

initial begin
    $dumpfile("PasswordLockFSM.vcd");
    $dumpvars(0, PasswordLockFSM_tb);

    reset = 1; key_valid = 0; admin_mode = 0;
    #20 reset = 0;

    // ✅ Correct password: A5 3 C
    $display("✅ Entering correct password");
    enter_password(16'b1010010100111100);
    #40;

    // ❌ Wrong attempts
    $display("❌ Wrong attempt 1");
    enter_password(16'b0000000000000000); #40;
    $display("❌ Wrong attempt 2");
    enter_password(16'b0000000000000000); #40;
    $display("❌ Wrong attempt 3 - should lock");
    enter_password(16'b0000000000000000); #100;

    // 🔧 Admin mode: Change password to 1 2 3 4
    admin_mode = 1;
    $display("🔧 Admin sets new password: 1 2 3 4");
    enter_password(16'b0001001000110100);
    admin_mode = 0; #40;

    // ✅ Test new password
    $display("✅ Trying new password: 1 2 3 4");
    enter_password(16'b0001001000110100);
    #40;

    $finish;
end

endmodule

PasswordLockFSM.vcd
$date
	Sat Jun 21 02:20:56 2025
$end
$version
	Icarus Verilog
$end
$timescale
	1ps
$end
$scope module PasswordLockFSM_tb $end
$var wire 1 ! unlock $end
$var wire 3 " state [2:0] $end
$var wire 1 # locked_out $end
$var wire 1 $ error_led $end
$var reg 1 % admin_mode $end
$var reg 1 & clk $end
$var reg 4 ' key_in [3:0] $end
$var reg 1 ( key_valid $end
$var reg 1 ) reset $end
$scope module dut $end
$var wire 1 % admin_mode $end
$var wire 1 & clk $end
$var wire 4 * key_in [3:0] $end
$var wire 1 ( key_valid $end
$var wire 1 ) reset $end
$var wire 1 + input_timeout $end
$var parameter 3 , IDLE $end
$var parameter 3 - INPUT_1 $end
$var parameter 3 . INPUT_2 $end
$var parameter 3 / INPUT_3 $end
$var parameter 3 0 INPUT_4 $end
$var parameter 3 1 LOCKED $end
$var parameter 3 2 UNLOCKED $end
$var reg 2 3 attempt_count [1:0] $end
$var reg 1 $ error_led $end
$var reg 2 4 input_index [1:0] $end
$var reg 1 # locked_out $end
$var reg 4 5 lockout_timer [3:0] $end
$var reg 3 6 state [2:0] $end
$var reg 4 7 timeout_counter [3:0] $end
$var reg 1 ! unlock $end
$var integer 32 8 i [31:0] $end
$upscope $end
$scope task enter_password $end
$var reg 16 9 password [15:0] $end
$var integer 32 : i [31:0] $end
$upscope $end
$upscope $end
$enddefinitions $end
$comment Show the parameter values. $end
$dumpall
b101 2
b110 1
b100 0
b11 /
b10 .
b1 -
b0 ,
$end
#0
$dumpvars
bx :
bx 9
bx 8
b0 7
b0 6
b0 5
bx 4
b0 3
0+
bx *
1)
0(
bx '
0&
0%
0$
0#
b0 "
0!
$end
#5000
1&
#10000
0&
#15000
1&
#20000
0&
1(
b1010 '
b1010 *
b1100 :
b1010010100111100 9
0)
#25000
b1 "
b1 6
b1 4
b0 7
1&
#30000
0&
0(
#35000
b1 7
1&
#40000
0&
1(
b101 '
b101 *
b1000 :
#45000
b10 "
b10 6
b10 4
b0 7
1&
#50000
0&
0(
#55000
b1 7
1&
#60000
0&
1(
b11 '
b11 *
b100 :
#65000
b11 "
b11 6
b11 4
b0 7
1&
#70000
0&
0(
#75000
b1 7
1&
#80000
0&
1(
b1100 '
b1100 *
b0 :
#85000
b100 "
b100 6
b0 4
b0 7
1&
#90000
0&
0(
#95000
b1 7
1&
#100000
0&
b11111111111111111111111111111100 :
#105000
b10 7
1&
#110000
0&
#115000
b11 7
1&
#120000
0&
#125000
b100 7
1&
#130000
0&
#135000
b101 7
1&
#140000
0&
1(
b0 '
b0 *
b1100 :
b0 9
#145000
b101 "
b101 6
1!
b0 7
1&
#150000
0&
0(
#155000
b0 "
b0 6
0!
b1 7
1&
#160000
0&
1(
b1000 :
#165000
b1 "
b1 6
b1 4
b0 7
1&
#170000
0&
0(
#175000
b1 7
1&
#180000
0&
1(
b100 :
#185000
b10 "
b10 6
b10 4
b0 7
1&
#190000
0&
0(
#195000
b1 7
1&
#200000
0&
1(
b0 :
#205000
b11 "
b11 6
b11 4
b0 7
1&
#210000
0&
0(
#215000
b1 7
1&
#220000
0&
b11111111111111111111111111111100 :
#225000
b10 7
1&
#230000
0&
#235000
b11 7
1&
#240000
0&
#245000
b100 7
1&
#250000
0&
#255000
b101 7
1&
#260000
0&
1(
b1100 :
#265000
b100 "
b100 6
b0 4
b0 7
1&
#270000
0&
0(
#275000
b1 7
1&
#280000
0&
1(
b1000 :
#285000
b0 "
b0 6
1$
b1 3
b0 7
1&
#290000
0&
0(
#295000
0$
b1 7
1&
#300000
0&
1(
b100 :
#305000
b1 "
b1 6
b1 4
b0 7
1&
#310000
0&
0(
#315000
b1 7
1&
#320000
0&
1(
b0 :
#325000
b10 "
b10 6
b10 4
b0 7
1&
#330000
0&
0(
#335000
b1 7
1&
#340000
0&
b11111111111111111111111111111100 :
#345000
b10 7
1&
#350000
0&
#355000
b11 7
1&
#360000
0&
#365000
b100 7
1&
#370000
0&
#375000
b101 7
1&
#380000
0&
1(
b1100 :
#385000
b11 "
b11 6
b11 4
b0 7
1&
#390000
0&
0(
#395000
b1 7
1&
#400000
0&
1(
b1000 :
#405000
b100 "
b100 6
b0 4
b0 7
1&
#410000
0&
0(
#415000
b1 7
1&
#420000
0&
1(
b100 :
#425000
b0 "
b0 6
1$
b10 3
b0 7
1&
#430000
0&
0(
#435000
0$
b1 7
1&
#440000
0&
1(
b0 :
#445000
b1 "
b1 6
b1 4
b0 7
1&
#450000
0&
0(
#455000
b1 7
1&
#460000
0&
b11111111111111111111111111111100 :
#465000
b10 7
1&
#470000
0&
#475000
b11 7
1&
#480000
0&
#485000
b100 7
1&
#490000
0&
#495000
b101 7
1&
#500000
0&
#505000
b110 7
1&
#510000
0&
#515000
b111 7
1&
#520000
0&
#525000
b1000 7
1&
#530000
0&
#535000
b1001 7
1&
#540000
0&
#545000
1+
b1010 7
1&
#550000
0&
#555000
b0 "
b0 6
b1011 7
1&
#560000
0&
1(
b1 '
b1 *
b1100 :
b1001000110100 9
1%
#565000
0+
b1 "
b1 6
b1 4
b0 7
1&
#570000
0&
0(
#575000
b1 7
1&
#580000
0&
1(
b10 '
b10 *
b1000 :
#585000
b10 "
b10 6
b10 4
b0 7
1&
#590000
0&
0(
#595000
b1 7
1&
#600000
0&
1(
b11 '
b11 *
b100 :
#605000
b11 "
b11 6
b11 4
b0 7
1&
#610000
0&
0(
#615000
b1 7
1&
#620000
0&
1(
b100 '
b100 *
b0 :
#625000
b100 "
b100 6
b0 4
b0 7
1&
#630000
0&
0(
#635000
b1 7
1&
#640000
0&
0%
b11111111111111111111111111111100 :
#645000
b10 7
1&
#650000
0&
#655000
b11 7
1&
#660000
0&
#665000
b100 7
1&
#670000
0&
#675000
b101 7
1&
#680000
0&
1(
b1 '
b1 *
b1100 :
#685000
b110 "
b110 6
b1010 5
1#
1$
b11 3
b0 7
1&
#690000
0&
0(
#695000
b1001 5
b1 7
1&
#700000
0&
1(
b10 '
b10 *
b1000 :
#705000
b1000 5
b10 7
1&
#710000
0&
0(
#715000
b111 5
b11 7
1&
#720000
0&
1(
b11 '
b11 *
b100 :
#725000
b110 5
b100 7
1&
#730000
0&
0(
#735000
b101 5
b101 7
1&
#740000
0&
1(
b100 '
b100 *
b0 :
#745000
b100 5
b110 7
1&
#750000
0&
0(
#755000
b11 5
b111 7
1&
#760000
0&
b11111111111111111111111111111100 :
#765000
b10 5
b1000 7
1&
#770000
0&
#775000
b1 5
b1001 7
1&
#780000
0&
#785000
b0 5
1+
b1010 7
1&
#790000
0&
#795000
b0 "
b0 6
b0 3
0#
b1111 5
b1011 7
1&
